dbt_contracts/__init__.py
dbt_contracts/_core.py
dbt_contracts/cli.py
dbt_contracts/dbt_cli.py
dbt_contracts/properties.py
dbt_contracts/runner.py
dbt_contracts/types.py
dbt_contracts/contracts/__init__.py
dbt_contracts/contracts/_contracts.py
dbt_contracts/contracts/_core.py
dbt_contracts/contracts/matchers.py
dbt_contracts/contracts/result.py
dbt_contracts/contracts/utils.py
dbt_contracts/contracts/conditions/__init__.py
dbt_contracts/contracts/conditions/_core.py
dbt_contracts/contracts/conditions/properties.py
dbt_contracts/contracts/conditions/source.py
dbt_contracts/contracts/generators/__init__.py
dbt_contracts/contracts/generators/_core.py
dbt_contracts/contracts/generators/column.py
dbt_contracts/contracts/generators/model.py
dbt_contracts/contracts/generators/node.py
dbt_contracts/contracts/generators/properties.py
dbt_contracts/contracts/generators/source.py
dbt_contracts/contracts/terms/__init__.py
dbt_contracts/contracts/terms/_core.py
dbt_contracts/contracts/terms/column.py
dbt_contracts/contracts/terms/macro.py
dbt_contracts/contracts/terms/model.py
dbt_contracts/contracts/terms/node.py
dbt_contracts/contracts/terms/properties.py
dbt_contracts/contracts/terms/source.py
dbt_contracts/formatters/__init__.py
dbt_contracts/formatters/_core.py
dbt_contracts/formatters/table.py
dbt_contracts-1.0.9.dist-info/METADATA
dbt_contracts-1.0.9.dist-info/WHEEL
dbt_contracts-1.0.9.dist-info/entry_points.txt
dbt_contracts-1.0.9.dist-info/licenses/LICENSE
dbt_contracts-1.0.9.dist-info/RECORD
