Metadata-Version: 2.4
Name: dbt-contracts
Version: 1.0.9
Summary: Enforce standards for your dbt projects through automated checks and generators
Project-URL: Documentation, https://geo-martino.github.io/dbt-contracts/
Project-URL: Release Notes, https://geo-martino.github.io/dbt-contracts/info/release-history.html
Project-URL: Contribute, https://geo-martino.github.io/dbt-contracts/info/contributing.html
Project-URL: Source code, https://github.com/geo-martino/dbt-contracts
Project-URL: Issues, https://github.com/geo-martino/dbt-contracts/issues
Author-email: George Martin Marino <gm.engineer+dbt-contracts@pm.me>
License-File: LICENSE
Classifier: Development Status :: 5 - Production/Stable
Classifier: Intended Audience :: Developers
Classifier: License :: OSI Approved :: MIT License
Classifier: Natural Language :: English
Classifier: Operating System :: MacOS :: MacOS X
Classifier: Operating System :: Microsoft :: Windows
Classifier: Operating System :: POSIX :: Linux
Classifier: Programming Language :: Python :: 3.12
Classifier: Programming Language :: Python :: 3.13
Requires-Python: >=3.12
Requires-Dist: dbt-core<2.0,>=1.9
Requires-Dist: pydantic<3.0,>=2.10
